{
  "content": [
    {
      "content": null,
      "created": "2026-04-13T01:28:32.381994Z",
      "format": null,
      "hash": null,
      "hash_algorithm": null,
      "last_modified": "2026-04-13T01:26:09.898228Z",
      "mimetype": "image/webp",
      "name": "ML-CheatSheet-01.webp",
      "path": "00-IntroductionCourseML/figs/ML-CheatSheet-01.webp",
      "size": 73128,
      "type": "file",
      "writable": true
    },
    {
      "content": null,
      "created": "2026-04-13T01:28:32.380173Z",
      "format": null,
      "hash": null,
      "hash_algorithm": null,
      "last_modified": "2026-04-13T01:26:09.896544Z",
      "mimetype": "image/png",
      "name": "AI-ML.png",
      "path": "00-IntroductionCourseML/figs/AI-ML.png",
      "size": 152081,
      "type": "file",
      "writable": true
    },
    {
      "content": null,
      "created": "2026-04-13T01:28:32.382408Z",
      "format": null,
      "hash": null,
      "hash_algorithm": null,
      "last_modified": "2026-04-13T01:26:09.898228Z",
      "mimetype": "image/png",
      "name": "ML-workflow.png",
      "path": "00-IntroductionCourseML/figs/ML-workflow.png",
      "size": 105546,
      "type": "file",
      "writable": true
    },
    {
      "content": null,
      "created": "2026-04-13T01:28:32.381462Z",
      "format": null,
      "hash": null,
      "hash_algorithm": null,
      "last_modified": "2026-04-13T01:26:09.897289Z",
      "mimetype": "image/png",
      "name": "DataPreprocessing.png",
      "path": "00-IntroductionCourseML/figs/DataPreprocessing.png",
      "size": 115284,
      "type": "file",
      "writable": true
    },
    {
      "content": null,
      "created": "2026-04-13T01:28:32.382948Z",
      "format": null,
      "hash": null,
      "hash_algorithm": null,
      "last_modified": "2026-04-13T01:26:09.898228Z",
      "mimetype": "image/png",
      "name": "tasks-xkcd.png",
      "path": "00-IntroductionCourseML/figs/tasks-xkcd.png",
      "size": 29585,
      "type": "file",
      "writable": true
    },
    {
      "content": null,
      "created": "2026-04-13T01:28:32.380854Z",
      "format": null,
      "hash": null,
      "hash_algorithm": null,
      "last_modified": "2026-04-13T01:26:09.897289Z",
      "mimetype": "image/png",
      "name": "Course-Contents.png",
      "path": "00-IntroductionCourseML/figs/Course-Contents.png",
      "size": 158035,
      "type": "file",
      "writable": true
    }
  ],
  "created": "2026-04-13T01:28:32.382553Z",
  "format": "json",
  "hash": null,
  "hash_algorithm": null,
  "last_modified": "2026-04-13T01:28:32.382553Z",
  "mimetype": null,
  "name": "figs",
  "path": "00-IntroductionCourseML/figs",
  "size": null,
  "type": "directory",
  "writable": true
}