{
  "content": [
    {
      "content": null,
      "created": "2026-02-15T05:00:24.804146Z",
      "format": null,
      "hash": null,
      "hash_algorithm": null,
      "last_modified": "2026-02-15T04:59:35.894771Z",
      "mimetype": "text/x-python",
      "name": "Point3D.py",
      "path": "01-reviewPython/Point3D.py",
      "size": 586,
      "type": "file",
      "writable": true
    },
    {
      "content": null,
      "created": "2026-02-15T05:00:24.803886Z",
      "format": null,
      "hash": null,
      "hash_algorithm": null,
      "last_modified": "2026-02-15T04:58:02.725561Z",
      "mimetype": null,
      "name": "02-IntroProgrammingPython-DataStructs.ipynb",
      "path": "01-reviewPython/02-IntroProgrammingPython-DataStructs.ipynb",
      "size": 24875,
      "type": "notebook",
      "writable": true
    },
    {
      "content": null,
      "created": "2026-02-15T05:00:24.809045Z",
      "format": null,
      "hash": null,
      "hash_algorithm": null,
      "last_modified": "2026-02-15T04:59:43.299629Z",
      "mimetype": "text/csv",
      "name": "test.csv",
      "path": "01-reviewPython/test.csv",
      "size": 542,
      "type": "file",
      "writable": true
    },
    {
      "content": null,
      "created": "2026-02-15T05:00:24.803604Z",
      "format": null,
      "hash": null,
      "hash_algorithm": null,
      "last_modified": "2026-02-15T04:58:02.724538Z",
      "mimetype": null,
      "name": "01-IntroProgrammingPython.ipynb",
      "path": "01-reviewPython/01-IntroProgrammingPython.ipynb",
      "size": 19816,
      "type": "notebook",
      "writable": true
    },
    {
      "content": null,
      "created": "2026-02-15T05:00:24.804552Z",
      "format": null,
      "hash": null,
      "hash_algorithm": null,
      "last_modified": "2026-02-15T04:59:36.893095Z",
      "mimetype": "text/x-python",
      "name": "example.py",
      "path": "01-reviewPython/example.py",
      "size": 440,
      "type": "file",
      "writable": true
    },
    {
      "content": null,
      "created": "2026-02-15T05:00:24.808794Z",
      "format": null,
      "hash": null,
      "hash_algorithm": null,
      "last_modified": "2026-02-15T04:58:02.728539Z",
      "mimetype": null,
      "name": "pandas-intro.ipynb",
      "path": "01-reviewPython/pandas-intro.ipynb",
      "size": 27042,
      "type": "notebook",
      "writable": true
    },
    {
      "content": null,
      "created": "2026-02-15T05:00:24.807012Z",
      "format": null,
      "hash": null,
      "hash_algorithm": null,
      "last_modified": "2026-02-15T05:00:24.807012Z",
      "mimetype": null,
      "name": "fig",
      "path": "01-reviewPython/fig",
      "size": null,
      "type": "directory",
      "writable": true
    },
    {
      "content": null,
      "created": "2026-02-15T05:00:24.809225Z",
      "format": null,
      "hash": null,
      "hash_algorithm": null,
      "last_modified": "2026-02-15T04:59:43.360023Z",
      "mimetype": "application/vnd.openxmlformats-officedocument.spreadsheetml.sheet",
      "name": "test.xlsx",
      "path": "01-reviewPython/test.xlsx",
      "size": 5342,
      "type": "file",
      "writable": true
    },
    {
      "content": null,
      "created": "2026-02-15T05:00:24.804330Z",
      "format": null,
      "hash": null,
      "hash_algorithm": null,
      "last_modified": "2026-02-15T04:58:02.725561Z",
      "mimetype": null,
      "name": "PythonReview.ipynb",
      "path": "01-reviewPython/PythonReview.ipynb",
      "size": 24166,
      "type": "notebook",
      "writable": true
    },
    {
      "content": null,
      "created": "2026-02-15T05:00:24.808586Z",
      "format": null,
      "hash": null,
      "hash_algorithm": null,
      "last_modified": "2026-02-15T04:59:42.541025Z",
      "mimetype": "application/pdf",
      "name": "fig.pdf",
      "path": "01-reviewPython/fig.pdf",
      "size": 12858,
      "type": "file",
      "writable": true
    }
  ],
  "created": "2026-02-15T05:00:24.809045Z",
  "format": "json",
  "hash": null,
  "hash_algorithm": null,
  "last_modified": "2026-02-15T05:00:24.809045Z",
  "mimetype": null,
  "name": "01-reviewPython",
  "path": "01-reviewPython",
  "size": null,
  "type": "directory",
  "writable": true
}