{
  "content": [
    {
      "content": null,
      "created": "2026-02-15T04:25:43.037663Z",
      "format": null,
      "hash": null,
      "hash_algorithm": null,
      "last_modified": "2026-02-15T04:25:43.037663Z",
      "mimetype": null,
      "name": "neuralnetwork",
      "path": "07-IntroNeuralNetworks/fig/neuralnetwork",
      "size": null,
      "type": "directory",
      "writable": true
    },
    {
      "content": null,
      "created": "2026-02-15T04:25:43.038990Z",
      "format": null,
      "hash": null,
      "hash_algorithm": null,
      "last_modified": "2026-02-15T04:23:20.170694Z",
      "mimetype": "image/png",
      "name": "nn-shallow.png",
      "path": "07-IntroNeuralNetworks/fig/nn-shallow.png",
      "size": 47651,
      "type": "file",
      "writable": true
    },
    {
      "content": null,
      "created": "2026-02-15T04:25:43.040596Z",
      "format": null,
      "hash": null,
      "hash_algorithm": null,
      "last_modified": "2026-02-15T04:23:20.171694Z",
      "mimetype": "image/png",
      "name": "tensorflow-playground.png",
      "path": "07-IntroNeuralNetworks/fig/tensorflow-playground.png",
      "size": 235091,
      "type": "file",
      "writable": true
    },
    {
      "content": null,
      "created": "2026-02-15T04:25:43.026368Z",
      "format": null,
      "hash": null,
      "hash_algorithm": null,
      "last_modified": "2026-02-15T04:23:20.161694Z",
      "mimetype": "image/png",
      "name": "cnn-3d.png",
      "path": "07-IntroNeuralNetworks/fig/cnn-3d.png",
      "size": 672046,
      "type": "file",
      "writable": true
    },
    {
      "content": null,
      "created": "2026-02-15T04:25:43.028702Z",
      "format": null,
      "hash": null,
      "hash_algorithm": null,
      "last_modified": "2026-02-15T04:23:20.162694Z",
      "mimetype": "image/png",
      "name": "deeplearning-history.png",
      "path": "07-IntroNeuralNetworks/fig/deeplearning-history.png",
      "size": 142014,
      "type": "file",
      "writable": true
    },
    {
      "content": null,
      "created": "2026-02-15T04:25:43.028233Z",
      "format": null,
      "hash": null,
      "hash_algorithm": null,
      "last_modified": "2026-02-15T04:23:20.161694Z",
      "mimetype": "image/png",
      "name": "cnn.png",
      "path": "07-IntroNeuralNetworks/fig/cnn.png",
      "size": 73782,
      "type": "file",
      "writable": true
    },
    {
      "content": null,
      "created": "2026-02-15T04:25:43.040069Z",
      "format": null,
      "hash": null,
      "hash_algorithm": null,
      "last_modified": "2026-02-15T04:23:20.170694Z",
      "mimetype": "image/svg+xml",
      "name": "nn.svg",
      "path": "07-IntroNeuralNetworks/fig/nn.svg",
      "size": 93153,
      "type": "file",
      "writable": true
    },
    {
      "content": null,
      "created": "2026-02-15T04:25:43.039434Z",
      "format": null,
      "hash": null,
      "hash_algorithm": null,
      "last_modified": "2026-02-15T04:23:20.170694Z",
      "mimetype": "text/x-tex",
      "name": "nn-shallow.tex",
      "path": "07-IntroNeuralNetworks/fig/nn-shallow.tex",
      "size": 1943,
      "type": "file",
      "writable": true
    },
    {
      "content": null,
      "created": "2026-02-15T04:25:43.029307Z",
      "format": null,
      "hash": null,
      "hash_algorithm": null,
      "last_modified": "2026-02-15T04:23:20.164694Z",
      "mimetype": "image/png",
      "name": "loss-01.png",
      "path": "07-IntroNeuralNetworks/fig/loss-01.png",
      "size": 974717,
      "type": "file",
      "writable": true
    },
    {
      "content": null,
      "created": "2026-02-15T04:25:43.023423Z",
      "format": null,
      "hash": null,
      "hash_algorithm": null,
      "last_modified": "2026-02-15T04:23:20.158694Z",
      "mimetype": "image/png",
      "name": "SGD.png",
      "path": "07-IntroNeuralNetworks/fig/SGD.png",
      "size": 1132710,
      "type": "file",
      "writable": true
    },
    {
      "content": null,
      "created": "2026-02-15T04:25:43.039781Z",
      "format": null,
      "hash": null,
      "hash_algorithm": null,
      "last_modified": "2026-02-15T04:23:20.170694Z",
      "mimetype": "text/x-tex",
      "name": "nn-tikz.tex",
      "path": "07-IntroNeuralNetworks/fig/nn-tikz.tex",
      "size": 1755,
      "type": "file",
      "writable": true
    },
    {
      "content": null,
      "created": "2026-02-15T04:25:43.032238Z",
      "format": null,
      "hash": null,
      "hash_algorithm": null,
      "last_modified": "2026-02-15T04:23:20.167694Z",
      "mimetype": "image/png",
      "name": "loss-02.png",
      "path": "07-IntroNeuralNetworks/fig/loss-02.png",
      "size": 2073804,
      "type": "file",
      "writable": true
    }
  ],
  "created": "2026-02-15T04:25:43.040238Z",
  "format": "json",
  "hash": null,
  "hash_algorithm": null,
  "last_modified": "2026-02-15T04:25:43.040238Z",
  "mimetype": null,
  "name": "fig",
  "path": "07-IntroNeuralNetworks/fig",
  "size": null,
  "type": "directory",
  "writable": true
}