{
  "content": [
    {
      "content": null,
      "created": "2026-03-10T23:32:39.885750Z",
      "format": null,
      "hash": null,
      "hash_algorithm": null,
      "last_modified": "2026-03-10T23:30:07.510487Z",
      "mimetype": null,
      "name": "DeepLearning.ipynb",
      "path": "07-IntroNeuralNetworks/DeepLearning.ipynb",
      "size": 43096,
      "type": "notebook",
      "writable": true
    },
    {
      "content": null,
      "created": "2026-03-10T23:32:39.903242Z",
      "format": null,
      "hash": null,
      "hash_algorithm": null,
      "last_modified": "2026-03-10T23:32:39.903242Z",
      "mimetype": null,
      "name": "fig",
      "path": "07-IntroNeuralNetworks/fig",
      "size": null,
      "type": "directory",
      "writable": true
    },
    {
      "content": null,
      "created": "2026-03-10T23:32:39.886146Z",
      "format": null,
      "hash": null,
      "hash_algorithm": null,
      "last_modified": "2026-03-10T23:30:07.510487Z",
      "mimetype": null,
      "name": "NeuralNetworks-BasicConcepts.ipynb",
      "path": "07-IntroNeuralNetworks/NeuralNetworks-BasicConcepts.ipynb",
      "size": 20103,
      "type": "notebook",
      "writable": true
    },
    {
      "content": null,
      "created": "2026-03-10T23:32:39.885408Z",
      "format": null,
      "hash": null,
      "hash_algorithm": null,
      "last_modified": "2026-03-10T23:30:07.508892Z",
      "mimetype": null,
      "name": "BackPropagation.ipynb",
      "path": "07-IntroNeuralNetworks/BackPropagation.ipynb",
      "size": 27892,
      "type": "notebook",
      "writable": true
    }
  ],
  "created": "2026-03-10T23:32:39.886146Z",
  "format": "json",
  "hash": null,
  "hash_algorithm": null,
  "last_modified": "2026-03-10T23:32:39.886146Z",
  "mimetype": null,
  "name": "07-IntroNeuralNetworks",
  "path": "07-IntroNeuralNetworks",
  "size": null,
  "type": "directory",
  "writable": true
}