{
  "content": [
    {
      "content": null,
      "created": "2026-02-15T04:25:43.022662Z",
      "format": null,
      "hash": null,
      "hash_algorithm": null,
      "last_modified": "2026-02-15T04:23:20.155643Z",
      "mimetype": null,
      "name": "DeepLearning.ipynb",
      "path": "07-IntroNeuralNetworks/DeepLearning.ipynb",
      "size": 43096,
      "type": "notebook",
      "writable": true
    },
    {
      "content": null,
      "created": "2026-02-15T04:25:43.040238Z",
      "format": null,
      "hash": null,
      "hash_algorithm": null,
      "last_modified": "2026-02-15T04:25:43.040238Z",
      "mimetype": null,
      "name": "fig",
      "path": "07-IntroNeuralNetworks/fig",
      "size": null,
      "type": "directory",
      "writable": true
    },
    {
      "content": null,
      "created": "2026-02-15T04:25:43.023042Z",
      "format": null,
      "hash": null,
      "hash_algorithm": null,
      "last_modified": "2026-02-15T04:23:20.155643Z",
      "mimetype": null,
      "name": "NeuralNetworks-BasicConcepts.ipynb",
      "path": "07-IntroNeuralNetworks/NeuralNetworks-BasicConcepts.ipynb",
      "size": 20103,
      "type": "notebook",
      "writable": true
    },
    {
      "content": null,
      "created": "2026-02-15T04:25:43.022302Z",
      "format": null,
      "hash": null,
      "hash_algorithm": null,
      "last_modified": "2026-02-15T04:23:20.154693Z",
      "mimetype": null,
      "name": "BackPropagation.ipynb",
      "path": "07-IntroNeuralNetworks/BackPropagation.ipynb",
      "size": 27892,
      "type": "notebook",
      "writable": true
    }
  ],
  "created": "2026-02-15T04:25:43.023042Z",
  "format": "json",
  "hash": null,
  "hash_algorithm": null,
  "last_modified": "2026-02-15T04:25:43.023042Z",
  "mimetype": null,
  "name": "07-IntroNeuralNetworks",
  "path": "07-IntroNeuralNetworks",
  "size": null,
  "type": "directory",
  "writable": true
}