{
  "content": [
    {
      "content": null,
      "created": "2026-02-15T18:17:25.435697Z",
      "format": null,
      "hash": null,
      "hash_algorithm": null,
      "last_modified": "2026-02-15T18:14:52.818927Z",
      "mimetype": null,
      "name": "DeepLearning.ipynb",
      "path": "07-IntroNeuralNetworks/DeepLearning.ipynb",
      "size": 43096,
      "type": "notebook",
      "writable": true
    },
    {
      "content": null,
      "created": "2026-02-15T18:17:25.455077Z",
      "format": null,
      "hash": null,
      "hash_algorithm": null,
      "last_modified": "2026-02-15T18:17:25.455077Z",
      "mimetype": null,
      "name": "fig",
      "path": "07-IntroNeuralNetworks/fig",
      "size": null,
      "type": "directory",
      "writable": true
    },
    {
      "content": null,
      "created": "2026-02-15T18:17:25.436071Z",
      "format": null,
      "hash": null,
      "hash_algorithm": null,
      "last_modified": "2026-02-15T18:14:52.818927Z",
      "mimetype": null,
      "name": "NeuralNetworks-BasicConcepts.ipynb",
      "path": "07-IntroNeuralNetworks/NeuralNetworks-BasicConcepts.ipynb",
      "size": 20103,
      "type": "notebook",
      "writable": true
    },
    {
      "content": null,
      "created": "2026-02-15T18:17:25.435354Z",
      "format": null,
      "hash": null,
      "hash_algorithm": null,
      "last_modified": "2026-02-15T18:14:52.817333Z",
      "mimetype": null,
      "name": "BackPropagation.ipynb",
      "path": "07-IntroNeuralNetworks/BackPropagation.ipynb",
      "size": 27892,
      "type": "notebook",
      "writable": true
    }
  ],
  "created": "2026-02-15T18:17:25.436071Z",
  "format": "json",
  "hash": null,
  "hash_algorithm": null,
  "last_modified": "2026-02-15T18:17:25.436071Z",
  "mimetype": null,
  "name": "07-IntroNeuralNetworks",
  "path": "07-IntroNeuralNetworks",
  "size": null,
  "type": "directory",
  "writable": true
}